mwaamt/.gitignore
mwaamt/LICENSE.txt
mwaamt/__init__.py
mwaamt/datahandle.py
mwaamt/flow.py
mwaamt/funk.py
mwaamt/files/config.json
mwaamt/files/m_paper_config.json
mwaamt/files/p_paper_config.json
mwaamt/files/.ipynb_checkpoints/fitres-checkpoint.csv
mwaamt/files/.ipynb_checkpoints/plot_alphabrc-checkpoint.ipynb
mwaamt-0.9.9.dist-info/entry_points.txt
mwaamt-0.9.9.dist-info/WHEEL
mwaamt-0.9.9.dist-info/METADATA
mwaamt-0.9.9.dist-info/RECORD
